wargaming/__init__.py
wargaming/exceptions.py
wargaming/meta.py
wargaming/parser.py
wargaming/settings.py
wargaming/version.py
wargaming/schema/wgn-schema.json
wargaming/schema/wot-schema.json
wargaming/schema/wotb-schema.json
wargaming/schema/wotx-schema.json
wargaming/schema/wowp-schema.json
wargaming/schema/wows-schema.json
wargaming-2018.5.0.dist-info/LICENSE.txt
wargaming-2018.5.0.dist-info/METADATA
wargaming-2018.5.0.dist-info/RECORD
wargaming-2018.5.0.dist-info/WHEEL
wargaming-2018.5.0.dist-info/top_level.txt
