Metadata-Version: 2.1
Name: wargaming
Version: 2018.5.0
Summary: API library for Wargaming.net
Home-page: https://github.com/svartalf/python-wargaming
Author: svartalf
Author-email: self@svartalf.info
License: MIT
Keywords: wargaming wot
Platform: UNKNOWN
Classifier: Development Status :: 3 - Alpha
Classifier: Intended Audience :: Developers
Classifier: License :: OSI Approved :: MIT License
Classifier: Operating System :: OS Independent
Classifier: Programming Language :: Python
Classifier: Programming Language :: Python :: 2.7
Classifier: Programming Language :: Python :: 3.4
Classifier: Programming Language :: Python :: 3.5
Classifier: Programming Language :: Python :: 3.6
Classifier: Programming Language :: Python :: Implementation :: PyPy
Classifier: Topic :: Software Development :: Libraries
Requires-Dist: six
Requires-Dist: requests
Requires-Dist: retrying
Requires-Dist: beautifulsoup4
